odoo/addons/sale_triple_discount/README.rst
odoo/addons/sale_triple_discount/__init__.py
odoo/addons/sale_triple_discount/__manifest__.py
odoo/addons/sale_triple_discount/i18n/ca.po
odoo/addons/sale_triple_discount/i18n/de.po
odoo/addons/sale_triple_discount/i18n/es.po
odoo/addons/sale_triple_discount/i18n/es_MX.po
odoo/addons/sale_triple_discount/i18n/es_VE.po
odoo/addons/sale_triple_discount/i18n/fr.po
odoo/addons/sale_triple_discount/i18n/hr.po
odoo/addons/sale_triple_discount/i18n/it.po
odoo/addons/sale_triple_discount/i18n/nl_NL.po
odoo/addons/sale_triple_discount/i18n/pt_BR.po
odoo/addons/sale_triple_discount/i18n/ro.po
odoo/addons/sale_triple_discount/i18n/sale_triple_discount.pot
odoo/addons/sale_triple_discount/i18n/sl.po
odoo/addons/sale_triple_discount/i18n/tr.po
odoo/addons/sale_triple_discount/i18n/tr_TR.po
odoo/addons/sale_triple_discount/models/__init__.py
odoo/addons/sale_triple_discount/models/sale_order_line.py
odoo/addons/sale_triple_discount/readme/CONFIGURE.rst
odoo/addons/sale_triple_discount/readme/CONTRIBUTORS.rst
odoo/addons/sale_triple_discount/readme/DESCRIPTION.rst
odoo/addons/sale_triple_discount/readme/USAGE.rst
odoo/addons/sale_triple_discount/static/description/icon.png
odoo/addons/sale_triple_discount/static/description/index.html
odoo/addons/sale_triple_discount/tests/__init__.py
odoo/addons/sale_triple_discount/tests/test_sale_triple_discount.py
odoo/addons/sale_triple_discount/views/sale_order_report.xml
odoo/addons/sale_triple_discount/views/sale_order_view.xml
odoo_addon_sale_triple_discount-16.0.1.0.6.dist-info/METADATA
odoo_addon_sale_triple_discount-16.0.1.0.6.dist-info/WHEEL
odoo_addon_sale_triple_discount-16.0.1.0.6.dist-info/top_level.txt
odoo_addon_sale_triple_discount-16.0.1.0.6.dist-info/RECORD
