Metadata-Version: 2.1
Name: odoo-addon-sale_triple_discount
Version: 16.0.1.0.6
Summary: Manage triple discount on sale order lines
Home-page: https://github.com/OCA/sale-workflow
Author: ADHOC SA, Agile Business Group, Tecnativa, Odoo Community Association (OCA)
Author-email: support@odoo-community.org
License: AGPL-3
Classifier: Programming Language :: Python
Classifier: Framework :: Odoo
Classifier: Framework :: Odoo :: 16.0
Classifier: License :: OSI Approved :: GNU Affero General Public License v3
Requires-Python: >=3.10
Requires-Dist: odoo-addon-account-invoice-triple-discount<16.0.3.0.0
Requires-Dist: odoo<16.1dev,>=16.0a
